[{"entity_group": "ORG", "score": "0.99514806", "word": "Ministerio de Ciencia, Innovacion y Universidades", "start": 61, "end": 110}, {"entity_group": "ORG", "score": "0.9998634", "word": "CSIC", "start": 140, "end": 144}, {"entity_group": "ORG", "score": "0.9998553", "word": "Australian Research Council", "start": 175, "end": 202}, {"entity_group": "ORG", "score": "0.99972457", "word": "Ministry of Education", "start": 255, "end": 276}, {"entity_group": "ORG", "score": "0.9973339", "word": "Science and Technological Development", "start": 278, "end": 315}, {"entity_group": "LOC", "score": "0.99431604", "word": "Republic of Serbia", "start": 346, "end": 364}, {"entity_group": "ORG", "score": "0.9997608", "word": "Ministry of Scientific and Technological Development", "start": 374, "end": 426}, {"entity_group": "ORG", "score": "0.99496365", "word": "Higher Education and Information Society", "start": 428, "end": 468}, {"entity_group": "LOC", "score": "0.9984607", "word": "Republic of Srpska", "start": 509, "end": 527}, {"entity_group": "LOC", "score": "0.99910235", "word": "Bosnia", "start": 529, "end": 535}, {"entity_group": "LOC", "score": "0.9129595", "word": "Herzegovina", "start": 541, "end": 552}, {"entity_group": "PER", "score": "0.99925154", "word": "L. Campbell", "start": 567, "end": 578}, {"entity_group": "PROY", "word": "Project No. FIS2016-80440),"}, {"entity_group": "PROY", "word": "Project No. LINKA20085),"}, {"entity_group": "PROY", "word": "Projects No. DP160102787"}, {"entity_group": "PROY", "word": "Project No. OI171020)"}, {"entity_group": "PROY", "word": "Project No. 19/6-020/961-67/18)"}, {"entity_group": "PROY", "word": "Project No."}, {"entity_group": "PROY", "word": "Project No."}, {"entity_group": "PROY", "word": "Projects No."}, {"entity_group": "PROY", "word": "Project No."}, {"entity_group": "PROY", "word": "Project No."}]